goompy/__init__.py
goompy/key.py
BetterGooMPy-1.dist-info/LICENSE
BetterGooMPy-1.dist-info/METADATA
BetterGooMPy-1.dist-info/WHEEL
BetterGooMPy-1.dist-info/top_level.txt
BetterGooMPy-1.dist-info/RECORD
